[
  {"category":"audio","name":"Micrófono AKG C-1000s","quantity":4},
  {"category":"audio","name":"Micrófono AKG C-3000","quantity":4},
  {"category":"audio","name":"Micrófono AKG C-451 b","quantity":2},
  {"category":"audio","name":"Micrófono AKG D-112","quantity":2},
  {"category":"audio","name":"Micrófono Audio Technica ATM-350","quantity":1},
  {"category":"audio","name":"Micrófono Audio Technica PRO-49QL","quantity":4},
  {"category":"audio","name":"Micrófono Audio Technica PRO-49Q","quantity":1},
  {"category":"audio","name":"Micrófono Audix OM7","quantity":1},
  {"category":"audio","name":"Micrófono DPA 4099-DC-1 (red)","quantity":4},
  {"category":"audio","name":"Micrófono IMG HSE-140/SK","quantity":4},
  {"category":"audio","name":"Micrófono IMG HSE-330/SK","quantity":26},
  {"category":"audio","name":"Micrófono Monacor HSE-700","quantity":2},
  {"category":"audio","name":"Micrófono Neumann KM-184","quantity":4},
  {"category":"audio","name":"Micrófono Neumann KMS-105","quantity":1},
  {"category":"audio","name":"Micrófono Prodipe BL-21","quantity":1},
  {"category":"audio","name":"Micrófono RODE NT-1A","quantity":4},
  {"category":"audio","name":"Micrófono RODE NT-G2","quantity":5},
  {"category":"audio","name":"Micrófono Sennheiser e604 grip","quantity":6},
  {"category":"audio","name":"Micrófono Sennheiser e608 pinza","quantity":1},
  {"category":"audio","name":"Micrófono Sennheiser e609 silver","quantity":2},
  {"category":"audio","name":"Micrófono Sennheiser e614","quantity":6},
  {"category":"audio","name":"Micrófono Sennheiser e835 S","quantity":5},
  {"category":"audio","name":"Micrófono Sennheiser e908 ew","quantity":3},
  {"category":"audio","name":"Micrófono Sennheiser HS-2 ew beige","quantity":7},
  {"category":"audio","name":"Micrófono Sennheiser HS-2 ew negro","quantity":1},
  {"category":"audio","name":"Micrófono Sennheiser ME2-US","quantity":5},
  {"category":"audio","name":"Micrófono Sennheiser ME3-II","quantity":8},
  {"category":"audio","name":"Micrófono Shure 55-SH","quantity":1},
  {"category":"audio","name":"Micrófono Shure Beta 52a","quantity":1},
  {"category":"audio","name":"Micrófono Shure Beta 58","quantity":2},
  {"category":"audio","name":"Micrófono Shure Beta 91a","quantity":4},
  {"category":"audio","name":"Micrófono Shure PG-185","quantity":2},
  {"category":"audio","name":"Micrófono Shure SM 57 LC","quantity":9},
  {"category":"audio","name":"Micrófono Shure SM 58 LC","quantity":8},
  {"category":"audio","name":"Micrófono Shure WL 185","quantity":8},
  {"category":"audio","name":"Altavoz CELESTION SR1 MK2 + tapa","quantity":12},
  {"category":"audio","name":"Altavoz CELESTION SR3","quantity":2},
  {"category":"audio","name":"Altavoz NEXO SIB-2000 Bass","quantity":6},
  {"category":"audio","name":"Altavoz NEXO SIMA-2000 Med-Agu.","quantity":6},
  {"category":"audio","name":"Altavoz NEXO PS-10","quantity":12},
  {"category":"audio","name":"Altavoz NEXO PS-15","quantity":7},
  {"category":"audio","name":"Altavoz VS-255PRO 1200W 4ohm","quantity":4},
  {"category":"audio","name":"Altavoz BEHRINGER B112 D","quantity":6},
  {"category":"audio","name":"Altavoz BEHRINGER B112 MP3","quantity":4},
  {"category":"audio","name":"Altavoz BEHRINGER B112 W","quantity":4},
  {"category":"audio","name":"Altavoz BEHRINGER B115 MP3","quantity":1},
  {"category":"audio","name":"Altavoz BEHRINGER B115 W","quantity":2},
  {"category":"audio","name":"Altavoz DAS Action 8A","quantity":4},
  {"category":"audio","name":"Altavoz DAS DR512a","quantity":8},
  {"category":"audio","name":"Altavoz EV ZLX-15BT","quantity":2},
  {"category":"audio","name":"Altavoz EV EKX-15P","quantity":4},
  {"category":"audio","name":"Altavoz EV ETX-35P","quantity":2},
  {"category":"audio","name":"Altavoz JBL IRX 108 BT","quantity":2},
  {"category":"audio","name":"Altavoz MACKIE ART500A","quantity":2},
  {"category":"audio","name":"Altavoz RCF HDL 30-A","quantity":12},
  {"category":"audio","name":"Subwoofer NEXO LS-500","quantity":2},
  {"category":"audio","name":"Subwoofer DAS Action 18A","quantity":2},
  {"category":"audio","name":"Subwoofer RCF Sub 705-AS II","quantity":4},
  {"category":"audio","name":"Subwoofer RCF Sub 9006-AS","quantity":4},
  {"category":"audio","name":"Bocina linea 100V AC-520T","quantity":61},
  {"category":"audio","name":"Bocina linea 100V IT-110","quantity":12},
  {"category":"audio","name":"Auricular Behringer HPM1000","quantity":4},
  {"category":"audio","name":"Auricular T.Bone HP66 Stereo","quantity":35},
  {"category":"audio","name":"Amplificador 100V A.C. 703","quantity":1},
  {"category":"audio","name":"Amplificador 100V A.C. 823","quantity":1},
  {"category":"audio","name":"Amplificador 100V Fonestar MA-30C","quantity":1},
  {"category":"audio","name":"Amplificador 100V BST UPA2150","quantity":1},
  {"category":"audio","name":"Amplificador 100V Monacor PA-9100D","quantity":2},
  {"category":"audio","name":"Amplificador CAMCO TECTON 28.2","quantity":5},
  {"category":"audio","name":"Amplificador CROWN Macro-Tech 602","quantity":2},
  {"category":"audio","name":"Amplificador CREST CPX-1500","quantity":3},
  {"category":"audio","name":"Amplificador DYNACORD L-2800FD","quantity":1},
  {"category":"audio","name":"Amplificador DYNACORD L-3600FD","quantity":1},
  {"category":"audio","name":"Amplificador LAB 1300","quantity":1},
  {"category":"audio","name":"Amplificador LAB 1600","quantity":3},
  {"category":"audio","name":"Amplificador LAB 2000C","quantity":1},
  {"category":"audio","name":"Amplificador LAB C 10:4X","quantity":1},
  {"category":"audio","name":"Amplificador LAB fp 3400 LA24","quantity":1},
  {"category":"audio","name":"Amplificador NEXO PS10AMP","quantity":2},
  {"category":"audio","name":"Amplificador Pioneer SA-V210","quantity":1},
  {"category":"audio","name":"Amplificador QSC MX-2000","quantity":2},
  {"category":"audio","name":"Amplificador QSC MX-2000a","quantity":4},
  {"category":"audio","name":"Amplificador QSC PL-1.8","quantity":1},
  {"category":"audio","name":"Amplificador SINMARC PA-1100N","quantity":1},
  {"category":"audio","name":"Amplificador guitarra FENDER FM 212R","quantity":2},
  {"category":"audio","name":"Amplificador bajo FENDER RUMBLE 100","quantity":1},
  {"category":"audio","name":"Batería PEARL EXPORT EX825","quantity":1},
  {"category":"audio","name":"Set de Platos ZILDJIAN ZBT 4 PRO","quantity":1},
  {"category":"video","name":"Reproductor CD PIONEER CDJ-2000 nexus","quantity":6},
  {"category":"video","name":"Reproductor CD PIONEER CDJ-2000 nexus2","quantity":2},
  {"category":"video","name":"Grabador Denon DN-300R MKII","quantity":1},
  {"category":"video","name":"Reproductor MP4 Philips","quantity":1},
  {"category":"video","name":"Controladora Denon DJ SC Live 4","quantity":1},
  {"category":"video","name":"Reproductor MP3 IMG CD-156","quantity":3},
  {"category":"video","name":"Reproductor MP3 MARK MMP5","quantity":2},
  {"category":"video","name":"Plato giradiscos TECHNICS SL-1210 M3D","quantity":2},
  {"category":"video","name":"Plato giradiscos TECHNICS SL-1210 mk7","quantity":2},
  {"category":"video","name":"Capsula Ortofon Concorde Mix","quantity":4},
  {"category":"video","name":"Grabadora Zoom P4","quantity":2},
  {"category":"video","name":"Cámara NIKON D5500 + Nikkor 18-140mm","quantity":1},
  {"category":"video","name":"Cámara MONACOR TVCCD-32MACOL","quantity":1},
  {"category":"video","name":"Cámara SONY HDR-CX240E","quantity":1},
  {"category":"video","name":"Pantalla táctil iiyama T2254-B1AG","quantity":1},
  {"category":"video","name":"Pantalla mural 200x200 DA-LITE","quantity":1},
  {"category":"video","name":"Pantalla trípode 240x180","quantity":1},
  {"category":"video","name":"Proyector EPSON EB-535W","quantity":1},
  {"category":"video","name":"Proyector EPSON EH-TW5600","quantity":1},
  {"category":"video","name":"Proyector Hitachi CP-X275","quantity":1},
  {"category":"video","name":"Proyector NEC M403H Full HD","quantity":1},
  {"category":"video","name":"Proyector NEC P502H Full HD","quantity":1},
  {"category":"video","name":"Proyector NEC PX800X","quantity":1},
  {"category":"video","name":"Optica NEC NP16FL","quantity":1},
  {"category":"video","name":"Optica NEC NP18ZL","quantity":1},
  {"category":"video","name":"Video Mixer Blackmagic ATEM Mini Pro","quantity":1},
  {"category":"video","name":"Cable VGA Male-Male 1.5m","quantity":1},
  {"category":"video","name":"Cable VGA Male-Male 20m","quantity":1},
  {"category":"video","name":"Cable HDMI 5m","quantity":3},
  {"category":"video","name":"Cable HDMI 10m","quantity":3},
  {"category":"video","name":"Cable coaxial BNC 5m","quantity":3},
  {"category":"luces","name":"SET Luces LED BossFX-2 Pro","quantity":4},
  {"category":"luces","name":"Foco PANORAMA 1000W asimétrico","quantity":12},
  {"category":"luces","name":"Foco PC 1Kw completo","quantity":12},
  {"category":"luces","name":"Foco Recorte ETC 575W JR-Zoom","quantity":8},
  {"category":"luces","name":"Foco ROCKET PAR-64 corto negro","quantity":28},
  {"category":"luces","name":"Foco ROCKET PAR-64 corto plata suelo","quantity":6},
  {"category":"luces","name":"Foco ROCKET PAR-64 largo negro","quantity":34},
  {"category":"luces","name":"Foco ROCKET PAR-64 corto plata","quantity":14},
  {"category":"luces","name":"Foco ROCKET PAR-64 largo plata","quantity":8},
  {"category":"luces","name":"Foco PANORAMA HMR 150W ARLÚS","quantity":18},
  {"category":"luces","name":"Foco PANORAMA HMR 150W TOLEDO","quantity":11},
  {"category":"luces","name":"Foco Cegadora 4 lamparas","quantity":2},
  {"category":"luces","name":"Foco Cegadora LED 2x100W","quantity":4},
  {"category":"luces","name":"Foco LED-PANORAMA Hekee 50W RGB IP66","quantity":2},
  {"category":"luces","name":"Foco LED Eurolite TL3","quantity":4},
  {"category":"luces","name":"Foco LED-PANORAMA 20W RGB mando","quantity":1},
  {"category":"luces","name":"Foco LED-PANORAMA 30W Blanco cálido","quantity":1},
  {"category":"luces","name":"Foco LED-PANORAMA 30W Blanco frío","quantity":8},
  {"category":"luces","name":"Foco LED-PANORAMA 50W Blanco cálido","quantity":20},
  {"category":"luces","name":"Foco LED-PANORAMA 50W Blanco frío","quantity":31},
  {"category":"luces","name":"Foco LED-PANORAMA Slim 50W FL5780","quantity":3},
  {"category":"luces","name":"Foco LED-PANORAMA Cameleon","quantity":4},
  {"category":"luces","name":"Foco LED COB PARC-100E/CTW","quantity":4},
  {"category":"luces","name":"Foco LED COB Eurolite 100 WW/CW","quantity":5},
  {"category":"luces","name":"Foco PAR-LED 60W RGB FRESNEL","quantity":1},
  {"category":"luces","name":"Foco PAR-LED 60W RGBWA Power Spot 6 Q5","quantity":18},
  {"category":"luces","name":"Foco PAR-LED 90W RGBWA LEDj","quantity":4},
  {"category":"luces","name":"Foco PAR-LED 90W RGBWA PC90","quantity":14},
  {"category":"luces","name":"Foco PAR-LED 90W RGBWA Power Spot 9 Q5","quantity":16},
  {"category":"luces","name":"Foco PAR-LED 180W RGBW ACSON","quantity":2},
  {"category":"luces","name":"Foco PAR-LED 270W PAR PRO 5-IN-1","quantity":8},
  {"category":"luces","name":"Foco PAR-LED 330W JNR-8160A FLAT","quantity":24},
  {"category":"luces","name":"Foco PAR-LED Spectra Par 7Q8 IP65","quantity":8},
  {"category":"luces","name":"Foco PAR-LED Spectra Par 15Q8 IP65","quantity":4},
  {"category":"luces","name":"Foco PAR-LED IP65 4in1 18x15 HY09","quantity":34},
  {"category":"luces","name":"Foco PAR-LED IP65 6in1 330W","quantity":3},
  {"category":"luces","name":"Foco PAR-LED Tour Spot ARC 18x8","quantity":35},
  {"category":"luces","name":"Foco PAR-LED-36 RGB","quantity":2},
  {"category":"luces","name":"Foco Panel LED 48W ColorPalet-II","quantity":1},
  {"category":"luces","name":"Foco Panel LED 96W CB 96","quantity":2},
  {"category":"luces","name":"Barra LED 100cm 18x10 RGBW IP65","quantity":1},
  {"category":"luces","name":"Foco LED batería Stairville BEL4","quantity":1},
  {"category":"luces","name":"Foco LED batería Free PAR Pro 72","quantity":48},
  {"category":"luces","name":"Foco LED batería NanGuang CN-600CSA","quantity":2},
  {"category":"luces","name":"Foco PAR-LED intemperie 4in1 18x18","quantity":72},
  {"category":"luces","name":"Foco PAR-LED intemperie 6in1 18x18","quantity":30},
  {"category":"luces","name":"Foco móvil Wash LED 5x15 RGBW+UV","quantity":2},
  {"category":"luces","name":"Foco móvil Wash Ibiza LMH350LED","quantity":4},
  {"category":"luces","name":"Foco móvil Wash AURA 19X15","quantity":8},
  {"category":"luces","name":"Foco móvil Wash Excalibur 285","quantity":8},
  {"category":"luces","name":"Foco móvil Spot Pro Light BSW200 LED","quantity":9},
  {"category":"luces","name":"Foco móvil Beam Pro Light XBEAM 10","quantity":4},
  {"category":"luces","name":"Foco scanner Martin MX1","quantity":2},
  {"category":"luces","name":"Laser PANDORA 1200","quantity":1},
  {"category":"luces","name":"Multirayo C-Mini Derby","quantity":6},
  {"category":"luces","name":"Multirayo C-Storm","quantity":2},
  {"category":"luces","name":"Multirayo C-Triple Derby","quantity":4},
  {"category":"luces","name":"Multirayo Martin WIZARD","quantity":1},
  {"category":"luces","name":"Multirayo Martin Mania EF1i","quantity":2},
  {"category":"luces","name":"Tubo ADJ LED Color Tube II","quantity":21},
  {"category":"luces","name":"Foco concentrador LED 15W","quantity":2},
  {"category":"luces","name":"Flash CHAUVET ST-3000 LED","quantity":2},
  {"category":"luces","name":"Flash Ibiza Light LS1500-DMX","quantity":1},
  {"category":"luces","name":"Flash KUPO E-2501","quantity":1},
  {"category":"luces","name":"Flash LED Strobo ST 60W","quantity":4},
  {"category":"luces","name":"Flash Pro Light Strobe 1500 DMX","quantity":1},
  {"category":"luces","name":"Bola de espejos 20cm","quantity":1},
  {"category":"luces","name":"Bola de espejos 30cm con motor","quantity":1},
  {"category":"luces","name":"Bola de espejos 40cm","quantity":1},
  {"category":"luces","name":"Bola de espejos 45cm Kupo","quantity":1},
  {"category":"luces","name":"Bola de espejos 50cm","quantity":1},
  {"category":"luces","name":"Mesa Luces AVOLITES TITAN T1","quantity":1},
  {"category":"luces","name":"Mesa Luces AVOLITES TITAN MOBILE","quantity":1},
  {"category":"luces","name":"Mesa Luces AVOLITES TITAN QUARTZ","quantity":1},
  {"category":"luces","name":"Mesa Luces BOTEX DC-1224","quantity":1},
  {"category":"luces","name":"Mesa Luces LSC Axiom 12","quantity":1},
  {"category":"luces","name":"Mesa Luces LT Piccolo-24","quantity":1},
  {"category":"luces","name":"Mesa Luces SHOWTEC Showmaster 48 MKII","quantity":1},
  {"category":"luces","name":"Mesa Luces Stairville DDC-12 LCD","quantity":1},
  {"category":"luces","name":"Mesa Luces Wolfmix Wi mk2","quantity":1},
  {"category":"luces","name":"Manguera SOCAPEX 10m","quantity":1},
  {"category":"luces","name":"Manguera SOCAPEX 15m","quantity":1},
  {"category":"luces","name":"Manguera SOCAPEX 20m","quantity":3},
  {"category":"luces","name":"Manguera SOCAPEX 25m","quantity":7},
  {"category":"luces","name":"Manguera SOCAPEX 35m","quantity":1},
  {"category":"luces","name":"Lámpara Atril SLED10","quantity":2},
  {"category":"luces","name":"Lámpara LED flexo 30cm XLR4","quantity":1},
  {"category":"estructuras","name":"Trípode Luces K&M 24610 manivela","quantity":2},
  {"category":"estructuras","name":"Trípode Luces K&M 24630","quantity":2},
  {"category":"estructuras","name":"Trípode Luces Manfrotto 1004BAC","quantity":3},
  {"category":"estructuras","name":"Trípode Luces WORK LW-125","quantity":12},
  {"category":"estructuras","name":"Torre elevadora 85Kg tipo Trípode","quantity":6},
  {"category":"estructuras","name":"Torre elevadora 100Kg TE-064","quantity":4},
  {"category":"estructuras","name":"Torre elevadora 200Kg TE-074","quantity":4},
  {"category":"estructuras","name":"Torre frontal 200Kg OMEGA-50","quantity":2},
  {"category":"estructuras","name":"Torre frontal 240Kg TL-072","quantity":4},
  {"category":"estructuras","name":"Base truss redonda 30Kg Trio/Deco","quantity":4},
  {"category":"estructuras","name":"Base truss cuadrado 307x307mm","quantity":8},
  {"category":"estructuras","name":"Base truss cuadrado 450x450mm","quantity":4},
  {"category":"estructuras","name":"Base truss cuadrado 600x600mm","quantity":8},
  {"category":"estructuras","name":"BULON Semi-Bulon Global Truss 5003","quantity":40},
  {"category":"estructuras","name":"Truss 2 vias 150cm Global Truss F32150","quantity":2},
  {"category":"estructuras","name":"Truss 2 vias PROLYTE X30L-L200","quantity":2},
  {"category":"estructuras","name":"TRUSS PROLYTE X30D-L050","quantity":2},
  {"category":"estructuras","name":"TRUSS PROLYTE X30D-L100","quantity":4},
  {"category":"estructuras","name":"TRUSS PROLYTE X30D-L150","quantity":4},
  {"category":"estructuras","name":"TRUSS PROLYTE X30D-L200","quantity":8},
  {"category":"estructuras","name":"TRUSS PROLYTE X30D-L300","quantity":10},
  {"category":"estructuras","name":"TRUSS PROLYTE FIGURA X30D C-012","quantity":2},
  {"category":"estructuras","name":"TRUSS PROLYTE FIGURA X30D C-013","quantity":2},
  {"category":"estructuras","name":"Truss cuadrado 29x29x050cm GT","quantity":4},
  {"category":"estructuras","name":"Truss cuadrado 29x29x100cm GT","quantity":4},
  {"category":"estructuras","name":"Truss cuadrado 29x29x150cm GT","quantity":4},
  {"category":"estructuras","name":"Truss cuadrado 29x29x200cm GT","quantity":6},
  {"category":"estructuras","name":"Truss cuadrado 29x29x300cm GT","quantity":4},
  {"category":"estructuras","name":"Global Truss F34Box Corner","quantity":4},
  {"category":"estructuras","name":"TRUSS rectangular VMB 240cm","quantity":4},
  {"category":"estructuras","name":"Tarima 100x100cm Nivoflex","quantity":2},
  {"category":"estructuras","name":"Tarima 200x100cm Nivoflex","quantity":10},
  {"category":"estructuras","name":"Tarima 200x100cm Nivoflex Light","quantity":4},
  {"category":"estructuras","name":"Pata telescópica tarima 60-100cm","quantity":56},
  {"category":"estructuras","name":"Pata fija tarima 40x4x4cm","quantity":24},
  {"category":"estructuras","name":"Carpa plegable 3x3 Enduro","quantity":2},
  {"category":"estructuras","name":"Toldo rafia Gris/Blau 6x10m","quantity":1},
  {"category":"estructuras","name":"Escalera aluminio 3x7","quantity":1},
  {"category":"estructuras","name":"Escalera aluminio 3x9","quantity":1},
  {"category":"estructuras","name":"Escalera aluminio 3x11","quantity":1},
  {"category":"estructuras","name":"Máquina Humo ARCUS 2000","quantity":2},
  {"category":"estructuras","name":"Máquina Humo DRACO 1500","quantity":1},
  {"category":"estructuras","name":"Máquina Humo MARK MF 900 MKII","quantity":3},
  {"category":"estructuras","name":"Máquina Humo MARK MF 1500","quantity":2},
  {"category":"estructuras","name":"Máquina Humo Smoke Factory Captain D","quantity":2},
  {"category":"estructuras","name":"Máquina Humo Smoke Factory DATA II","quantity":2},
  {"category":"estructuras","name":"Máquina Humo Stairville AF-150 DMX","quantity":6},
  {"category":"estructuras","name":"Máquina Humo Stairville M-Fog 1500","quantity":1},
  {"category":"estructuras","name":"Máquina niebla hazer Look UNIQUE 2.1","quantity":2},
  {"category":"estructuras","name":"Máquina Hazer Polaris 1500","quantity":2},
  {"category":"estructuras","name":"Máquina Humo ADJ Fog Fury Jett","quantity":6},
  {"category":"estructuras","name":"Generador Honda 2 Kw","quantity":1},
  {"category":"estructuras","name":"Generador MG-1000i II","quantity":3},
  {"category":"estructuras","name":"Mesa soporte audiovisuales PT-9","quantity":1},
  {"category":"estructuras","name":"Mesa catering plegable 183x76","quantity":2},
  {"category":"estructuras","name":"Atril metacrilato conferencias","quantity":1}
]
